vora/pairing.py
vora/scanning.py
vora/transform.py
vora/voronoi_2d.py
vora/voronoi_sphere.py
vora-0.1.0.dist-info/METADATA
vora-0.1.0.dist-info/WHEEL
vora-0.1.0.dist-info/top_level.txt
vora-0.1.0.dist-info/RECORD
