Metadata-Version: 2.4
Name: vora
Version: 0.1.0
Requires-Dist: numpy
Requires-Dist: h5py
Requires-Dist: matplotlib
Requires-Dist: pandas
Dynamic: description
Dynamic: description-content-type
Dynamic: requires-dist
